sgvn_sentry_auth_ldap/backend.py
sgvn_sentry_auth_ldap-23.6.1.dist-info/LICENSE.txt
sgvn_sentry_auth_ldap-23.6.1.dist-info/METADATA
sgvn_sentry_auth_ldap-23.6.1.dist-info/WHEEL
sgvn_sentry_auth_ldap-23.6.1.dist-info/top_level.txt
sgvn_sentry_auth_ldap-23.6.1.dist-info/RECORD
