Metadata-Version: 2.1
Name: sgvn-sentry-auth-ldap
Version: 23.6.1
Summary: A Sentry extension to add an LDAP server as an authentication source.
Home-page: https://github.com/PMExtra/sentry-auth-ldap
Download-URL: https://github.com/PMExtra/sentry-auth-ldap
Author: Chad Killingsworth <chad.killingsworth@banno.com>, Barron Hagerman <barron.hagerman@banno.com>, PM Extra <pm@jubeat.net>
Author-email: pm@jubeat.net
License: Apache-2.0
Project-URL: Bug Tracker, https://github.com/PMExtra/sentry-auth-ldap/issues
Project-URL: CI, https://github.com/PMExtra/sentry-auth-ldap/actions
Project-URL: Source Code, https://github.com/PMExtra/sentry-auth-ldap
Classifier: Framework :: Django
Classifier: Intended Audience :: Developers
Classifier: Intended Audience :: System Administrators
Classifier: Operating System :: OS Independent
Classifier: Programming Language :: Python :: 3
Classifier: Topic :: Software Development
License-File: LICENSE.txt
Requires-Dist: django-auth-ldap ==4.1.0
Requires-Dist: sentry >=23.6.0
